lsy_testcase_to_xmind_mcp/__init__.py
lsy_testcase_to_xmind_mcp-0.1.8.dist-info/WHEEL
lsy_testcase_to_xmind_mcp-0.1.8.dist-info/entry_points.txt
lsy_testcase_to_xmind_mcp-0.1.8.dist-info/METADATA
lsy_testcase_to_xmind_mcp-0.1.8.dist-info/RECORD
